LICENSE
tracktrace/__init__.py
tracktrace/ocean/__init__.py
tracktrace/ocean/anrm.py
tracktrace/ocean/aplu.py
tracktrace/ocean/base.py
tracktrace/ocean/cmdu.py
tracktrace/ocean/cosu.py
tracktrace/ocean/hlcu.py
tracktrace/ocean/maeu.py
tracktrace/ocean/mscu.py
tracktrace/ocean/ocean.py
tracktrace/ocean/oney.py
tracktrace/ocean/sudu.py
tracktrace/ocean/utils.py
tracktrace/rail/__init__.py
tracktrace/rail/csx.py
tracktrace/rail/rail.py
tracktrace/rail/utils.py
tracktrace-0.0.7.dist-info/LICENSE
tracktrace-0.0.7.dist-info/WHEEL
tracktrace-0.0.7.dist-info/METADATA
tracktrace-0.0.7.dist-info/RECORD
