Metadata-Version: 2.1
Name: tracktrace
Version: 0.0.7
Summary: Track and trace shipping containers across all major steamship lines
Home-page: https://github.com/dhruvkar/tracktrace
License: MIT
Keywords: shipping container,track,trace,cargo tracking
Author: Dhruv Kar
Author-email: dhruv@wints.org
Requires-Python: >=3.6,<4.0
Classifier: Development Status :: 3 - Alpha
Classifier: Environment :: Console
Classifier: License :: OSI Approved :: MIT License
Classifier: Natural Language :: English
Classifier: Operating System :: OS Independent
Classifier: Programming Language :: Python :: 3
Classifier: Programming Language :: Python :: 3.6
Classifier: Programming Language :: Python :: 3.7
Classifier: Programming Language :: Python :: 3.8
Classifier: Topic :: Office/Business :: Scheduling
Classifier: Topic :: Software Development :: Libraries :: Python Modules
Requires-Dist: beautifulsoup4 (>=4.9.3,<5.0.0)
Requires-Dist: bs4 (>=0.0.1,<0.0.2)
Requires-Dist: feedparser (>=6.0.2,<7.0.0)
Requires-Dist: html5lib (>=1.1,<2.0)
Requires-Dist: lxml (>=4.6.1,<5.0.0)
Requires-Dist: pandas (>=1.1.4,<2.0.0)
Requires-Dist: pendulum (>=2.1.2,<3.0.0)
Requires-Dist: requests (>=2.24.0,<3.0.0)
Project-URL: Documentation, https://github.com/dhruvkar/tracktrace
Project-URL: Repository, https://github.com/dhruvkar/tracktrace
